rhdllib/__init__.py
rhdllib/auth.py
rhdllib/metrics.py
rhdllib/version.py
rhdllib-0.1.0.post1769781378.dist-info/licenses/LICENSE
rhdllib-0.1.0.post1769781378.dist-info/METADATA
rhdllib-0.1.0.post1769781378.dist-info/WHEEL
rhdllib-0.1.0.post1769781378.dist-info/top_level.txt
rhdllib-0.1.0.post1769781378.dist-info/RECORD
