Metadata-Version: 2.4
Name: rhdllib
Version: 0.1.0.post1769781378
Summary: RHDL python module
Home-page: https://doc.rhdl.distributed-ci.io/
Author: Distributed CI team
Author-email: distributed-ci@redhat.com
License: Apache v2.0
Classifier: License :: OSI Approved :: Apache Software License
Classifier: Operating System :: POSIX :: Linux
Classifier: Programming Language :: Python :: 3
License-File: LICENSE
Requires-Dist: requests
Requires-Dist: statsd
Dynamic: author
Dynamic: author-email
Dynamic: classifier
Dynamic: description
Dynamic: description-content-type
Dynamic: home-page
Dynamic: license
Dynamic: license-file
Dynamic: requires-dist
Dynamic: summary
